dummy/__init__.py
dummy/main.py
dummy_module/__init__.py
dummy_module/main.py
dummy_module-0.0.2.dist-info/LICENSE
dummy_module-0.0.2.dist-info/METADATA
dummy_module-0.0.2.dist-info/WHEEL
dummy_module-0.0.2.dist-info/top_level.txt
dummy_module-0.0.2.dist-info/RECORD
