Metadata-Version: 2.1
Name: dummy_module
Version: 0.0.2
Summary: just a zero/dummy pypi package
Home-page: https://github.com/centroid457/
Author: Andrei Starichenko
Author-email: centroid@mail.ru
Project-URL: Source, https://github.com/centroid457/dummy_module
Keywords: dummy,dummy pypi,dummy pypi module,dummy pypi package,dummy pypi pkg,dummy module,dummy package,dummy pkg,blank module,blank package,blank pkg,zero module,zero package,zero pkg
Classifier: Topic :: Software Development :: Libraries :: Python Modules
Classifier: License :: OSI Approved :: MIT License
Classifier: Programming Language :: Python
Classifier: Programming Language :: Python :: 3 :: Only
Classifier: Programming Language :: Python :: 3.11
Classifier: Operating System :: OS Independent
Classifier: Intended Audience :: Developers
Classifier: Natural Language :: English
Classifier: Typing :: Typed
Requires-Python: >=3.6
License-File: LICENSE
